singlecellexperiment/SingleCellExperiment.py
singlecellexperiment/__init__.py
singlecellexperiment/_combineutils.py
singlecellexperiment/_ioutils.py
singlecellexperiment/io/__init__.py
singlecellexperiment/io/h5ad.py
singlecellexperiment/io/tenx.py
singlecellexperiment-0.6.2.dist-info/licenses/LICENSE.txt
singlecellexperiment-0.6.2.dist-info/METADATA
singlecellexperiment-0.6.2.dist-info/WHEEL
singlecellexperiment-0.6.2.dist-info/top_level.txt
singlecellexperiment-0.6.2.dist-info/RECORD
