Metadata-Version: 2.4
Name: SingleCellExperiment
Version: 0.6.2
Summary: Container class for single-cell experiments
Home-page: https://github.com/BiocPy/SingleCellExperiment
Author: jkanche
Author-email: jayaram.kancherla@gmail.com
License: MIT
Project-URL: Documentation, https://github.com/BiocPy/SingleCellExperiment
Platform: any
Classifier: Development Status :: 4 - Beta
Classifier: Programming Language :: Python
Requires-Python: >=3.9
License-File: LICENSE.txt
Requires-Dist: importlib-metadata; python_version < "3.8"
Requires-Dist: summarizedexperiment>=0.6.3
Requires-Dist: compressed-lists>=0.4.3
Provides-Extra: optional
Requires-Dist: anndata==0.9.2; python_version <= "3.9" and extra == "optional"
Requires-Dist: anndata>0.9.2; python_version > "3.9" and extra == "optional"
Requires-Dist: h5py; extra == "optional"
Requires-Dist: mudata==0.2.3; python_version <= "3.9" and extra == "optional"
Requires-Dist: mudata>0.2.3; python_version > "3.9" and extra == "optional"
Requires-Dist: delayedarray; extra == "optional"
Requires-Dist: hdf5array; extra == "optional"
Requires-Dist: numpy==1.24.4; python_version <= "3.9" and extra == "optional"
Requires-Dist: numpy>1.24.4; python_version > "3.9" and extra == "optional"
Provides-Extra: testing
Requires-Dist: setuptools; extra == "testing"
Requires-Dist: pytest; extra == "testing"
Requires-Dist: pytest-cov; extra == "testing"
Requires-Dist: anndata==0.9.2; python_version <= "3.9" and extra == "testing"
Requires-Dist: anndata>0.9.2; python_version > "3.9" and extra == "testing"
Requires-Dist: h5py; extra == "testing"
Requires-Dist: mudata==0.2.3; python_version <= "3.9" and extra == "testing"
Requires-Dist: mudata>0.2.3; python_version > "3.9" and extra == "testing"
Requires-Dist: delayedarray; extra == "testing"
Requires-Dist: hdf5array; extra == "testing"
Requires-Dist: numpy==1.24.4; python_version <= "3.9" and extra == "testing"
Requires-Dist: numpy>1.24.4; python_version > "3.9" and extra == "testing"
Dynamic: license-file
